gitlas/__init__.py
gitlas/core.py
gitlas-0.2.4.dist-info/LICENSE
gitlas-0.2.4.dist-info/METADATA
gitlas-0.2.4.dist-info/WHEEL
gitlas-0.2.4.dist-info/top_level.txt
gitlas-0.2.4.dist-info/RECORD
