Metadata-Version: 2.1
Name: gitlas
Version: 0.2.4
Summary: A minimalist git log Statistics library
Home-page: https://abhi-1u.github.io/gitlas/docs/
Author: Abhi-1U
Author-email: PerricoQ@outlook.com
License: MIT
Project-URL: Documentation, https://abhi-1u.github.io/gitlas/docs/
Project-URL: Source Code, https://github.com/Abhi-1U/gitlas
Platform: UNKNOWN
Classifier: Topic :: Scientific/Engineering :: Information Analysis
Classifier: Programming Language :: Python :: 3
Classifier: License :: OSI Approved :: MIT License
Classifier: Operating System :: OS Independent
Requires-Python: >=3.0
